emilie/__init__.py
emilie-0.0.3.data/scripts/emilie
emilie-0.0.3.dist-info/LICENSE
emilie-0.0.3.dist-info/METADATA
emilie-0.0.3.dist-info/WHEEL
emilie-0.0.3.dist-info/top_level.txt
emilie-0.0.3.dist-info/RECORD
