Metadata-Version: 2.1
Name: emilie
Version: 0.0.3
Summary: Meet Emilie
Home-page: https://gitlab.com/emilie/emilie
Author: Emilie Schario
Author-email: emilie.schario@gmail.com
License: UNKNOWN
Platform: UNKNOWN
Classifier: Programming Language :: Python :: 3
Classifier: License :: OSI Approved :: MIT License
Classifier: Operating System :: OS Independent
Requires-Python: >=3.6
